mangakakalot/__init__.py
mangakakalot/__main__.py
mangakakalot/errors.py
mangakakalot/manga.py
mangakakalot/manga_.py
mangakakalot/placki.py
mangakakalot.py-1.0.1.dist-info/LICENSE
mangakakalot.py-1.0.1.dist-info/METADATA
mangakakalot.py-1.0.1.dist-info/WHEEL
mangakakalot.py-1.0.1.dist-info/top_level.txt
mangakakalot.py-1.0.1.dist-info/RECORD
