Metadata-Version: 2.1
Name: mangakakalot.py
Version: 1.0.1
Summary: mangakakalot.py
Home-page: https://gitlab.com/webuby/mangakakalot.py
Author: webuby
Author-email: 
License: UNKNOWN
Keywords: manga mangakakalot mangakakalot.py anime mangakakalot.py
Platform: UNKNOWN
Classifier: Programming Language :: Python :: 3.8
Classifier: License :: OSI Approved :: MIT License
Classifier: Operating System :: OS Independent
Requires-Python: >=3.6
Requires-Dist: requests
Requires-Dist: beautifulsoup4
Requires-Dist: Pillow
